dju_image/__init__.py
dju_image/image.py
dju_image/maintenance.py
dju_image/settings.py
dju_image/tools.py
dju_image/views.py
dju_image/locale/en/LC_MESSAGES/django.po
dju_image/locale/ru/LC_MESSAGES/django.po
dju_image/locale/uk/LC_MESSAGES/django.po
dju_image/management/__init__.py
dju_image/management/commands/__init__.py
dju_image/management/commands/dju_image_remake_variants.py
dju_image/management/commands/dju_image_remove_old_tmp.py
dju_image/templatetags/__init__.py
dju_image/templatetags/dju_image.py
dju_image-0.1.18.dist-info/DESCRIPTION.rst
dju_image-0.1.18.dist-info/METADATA
dju_image-0.1.18.dist-info/RECORD
dju_image-0.1.18.dist-info/WHEEL
dju_image-0.1.18.dist-info/metadata.json
dju_image-0.1.18.dist-info/top_level.txt
