Metadata-Version: 2.0
Name: dju-image
Version: 0.1.18
Summary: Django Utils: Image Library
Home-page: https://github.com/liminspace/dju-image
Author: Igor Melnyk
Author-email: liminspace@gmail.com
License: MIT
Platform: UNKNOWN
Requires-Dist: dju-common
Requires-Dist: django (>=1.8.<1.11)
Requires-Dist: Pillow
